LICENSE
relational_stream/__init__.py
relational_stream/flow.py
relational_stream/py.typed
relational_stream/stream.py
relational_stream-0.6.0.dist-info/entry_points.txt
relational_stream-0.6.0.dist-info/LICENSE
relational_stream-0.6.0.dist-info/WHEEL
relational_stream-0.6.0.dist-info/METADATA
relational_stream-0.6.0.dist-info/RECORD
