Metadata-Version: 2.1
Name: relational-stream
Version: 0.6.0
Summary: A Python library for relational stream analysis.
Home-page: https://github.com/stephanlensky/python-relational-stream-analysis
License: GPL-3.0-only
Author: Stephan Lensky
Author-email: stephanl.public@gmail.com
Requires-Python: >=3.9,<4.0
Classifier: License :: OSI Approved :: GNU General Public License v3 (GPLv3)
Classifier: Programming Language :: Python :: 3
Classifier: Programming Language :: Python :: 3.10
Classifier: Programming Language :: Python :: 3.9
Requires-Dist: pytest (>=6.2.5,<7.0.0)
Project-URL: Repository, https://github.com/stephanlensky/python-relational-stream-analysis
